ioseeth/__init__.py
ioseeth/data/abi/interfaces/IERC20.json
ioseeth/data/abi/interfaces/IERC777.json
ioseeth/data/abi/interfaces/IUniswapV3Pool.json
ioseeth/data/abi/token/ERC1155/ERC1155.json
ioseeth/data/abi/token/ERC20/ERC20.json
ioseeth/data/abi/token/ERC721/ERC721.json
ioseeth/data/chains.json
ioseeth/evidence/__init__.py
ioseeth/indicators/__init__.py
ioseeth/indicators/batch.py
ioseeth/indicators/events.py
ioseeth/indicators/generic.py
ioseeth/indicators/metamorphism.py
ioseeth/indicators/proxy.py
ioseeth/indicators/redpill.py
ioseeth/indicators/token.py
ioseeth/indicators/wordlists.py
ioseeth/metrics/__init__.py
ioseeth/metrics/batch/__init__.py
ioseeth/metrics/batch/airdrop.py
ioseeth/metrics/batch/batch.py
ioseeth/metrics/batch/native.py
ioseeth/metrics/batch/token.py
ioseeth/metrics/evasion/__init__.py
ioseeth/metrics/evasion/morphing/__init__.py
ioseeth/metrics/evasion/morphing/logic_bomb.py
ioseeth/metrics/evasion/morphing/metamorphism.py
ioseeth/metrics/evasion/redirection.py
ioseeth/metrics/generic.py
ioseeth/metrics/normal/bridge.py
ioseeth/metrics/normal/dex.py
ioseeth/metrics/normal/pool.py
ioseeth/metrics/normal/proxy.py
ioseeth/metrics/normal/token.py
ioseeth/metrics/probabilities.py
ioseeth/parsing/__init__.py
ioseeth/parsing/abi.py
ioseeth/parsing/balances.py
ioseeth/parsing/bytecode.py
ioseeth/parsing/chains.py
ioseeth/parsing/events.py
ioseeth/parsing/inputs.py
ioseeth/scraping/__init__.py
ioseeth/scraping/bytecode.py
ioseeth/utils.py
ioseeth-0.1.22.dist-info/METADATA
ioseeth-0.1.22.dist-info/WHEEL
ioseeth-0.1.22.dist-info/RECORD
