Metadata-Version: 2.1
Name: ioseeth
Version: 0.1.22
Summary: Utilities to parse blockchain data and look for threat indicators
Author: apehex
Author-email: apehex@protonmail.com
Requires-Python: >=3.8,<4
Classifier: Programming Language :: Python :: 3
Classifier: Programming Language :: Python :: 3.8
Classifier: Programming Language :: Python :: 3.9
Classifier: Programming Language :: Python :: 3.10
Classifier: Programming Language :: Python :: 3.11
Classifier: Programming Language :: Python :: 3.12
Requires-Dist: setuptools (>=68)
Requires-Dist: toolblocks (>=0.5.0)
Requires-Dist: web3 (>=5)
